writepypistat/__init__.py
writepypistat/pypistat.py
writepypistat/statdate.py
write_pypistat-0.5.5.dist-info/LICENSE
write_pypistat-0.5.5.dist-info/METADATA
write_pypistat-0.5.5.dist-info/WHEEL
write_pypistat-0.5.5.dist-info/top_level.txt
write_pypistat-0.5.5.dist-info/RECORD
