Metadata-Version: 2.1
Name: write-pypistat
Version: 0.5.5
Summary: write-pypistat makes it easy to collect, filter and save pypi statistics to csv files.
Home-page: https://github.com/veghdev/write-pypistat
License: Apache 2.0
Project-URL: Documentation, https://github.com/veghdev/write-pypistat
Project-URL: Source, https://github.com/veghdev/write-pypistat
Project-URL: Tracker, https://github.com/veghdev/write-pypistat/issues
Classifier: Programming Language :: Python :: 3
Classifier: License :: OSI Approved :: Apache Software License
Classifier: Operating System :: OS Independent
Classifier: Environment :: Console
Requires-Python: >=3.6
License-File: LICENSE
Requires-Dist: numpy
Requires-Dist: pandas
Requires-Dist: pypistats
